jsonschema2rdbmsddl/__init__.py
jsonschema2rdbmsddl-0.0.1.dist-info/LICENSE
jsonschema2rdbmsddl-0.0.1.dist-info/METADATA
jsonschema2rdbmsddl-0.0.1.dist-info/WHEEL
jsonschema2rdbmsddl-0.0.1.dist-info/top_level.txt
jsonschema2rdbmsddl-0.0.1.dist-info/RECORD
